kpc_nifi_utils/__init__.py
kpc_nifi_utils/args/__init__.py
kpc_nifi_utils/args/aws.py
kpc_nifi_utils/args/mongodb.py
kpc_nifi_utils/args/mssql.py
kpc_nifi_utils/args/postgresql.py
kpc_nifi_utils/args/s3.py
kpc_nifi_utils/args/snowflake.py
kpc_nifi_utils/common/__init__.py
kpc_nifi_utils/common/args_parser.py
kpc_nifi_utils/common/json_encoder.py
kpc_nifi_utils/common/singleton.py
kpc_nifi_utils/connector/__init__.py
kpc_nifi_utils/connector/mongo_connector.py
kpc_nifi_utils/connector/mssql_connector.py
kpc_nifi_utils/connector/postgresql_connector.py
kpc_nifi_utils/connector/snowflake_connector.py
kpc_nifi_utils/nifi/__init__.py
kpc_nifi_utils/nifi/execute_stream_command.py
kpc_nifi_utils/parser/__init__.py
kpc_nifi_utils/parser/s3.py
kpc_nifi_utils/shared/__init__.py
kpc_nifi_utils/shared/constants.py
kpc_nifi_utils/shared/datetime.py
kpc_nifi_utils/shared/timezone.py
kpc_nifi_utils-0.3.1.dist-info/LICENSE.txt
kpc_nifi_utils-0.3.1.dist-info/METADATA
kpc_nifi_utils-0.3.1.dist-info/WHEEL
kpc_nifi_utils-0.3.1.dist-info/top_level.txt
kpc_nifi_utils-0.3.1.dist-info/RECORD
